Pext-0.35.data/data/share/applications/io.pext.pext.desktop
Pext-0.35.data/data/share/icons/hicolor/128x128/apps/pext.png
Pext-0.35.data/data/share/icons/hicolor/48x48/apps/pext.png
Pext-0.35.data/data/share/icons/hicolor/scalable/apps/pext.svg
Pext-0.35.data/data/share/metainfo/io.pext.pext.appdata.xml
pext/VERSION
pext/__init__.py
pext/__main__.py
pext/constants.py
pext/ui_qt5.py
pext/helpers/pext_base.py
pext/helpers/pext_helpers.py
pext/images/128x128/pext.png
pext/images/scalable/logo.svg
pext/images/scalable/pext.icns
pext/images/scalable/pext.ico
pext/images/scalable/pext.svg
pext/qml/AboutDialog.qml
pext/qml/ChoiceDialog.qml
pext/qml/CommandArgsDialog.qml
pext/qml/ConfirmQuitDialog.qml
pext/qml/CriticalErrorDialog.qml
pext/qml/InputRequestDialog.qml
pext/qml/InstallFromRepositoryDialog.qml
pext/qml/InstallModuleFromRepositoryNoModulesAvailableDialog.qml
pext/qml/InstallModuleFromRepositorySelectModuleDialog.qml
pext/qml/InstallModuleFromURLDialog.qml
pext/qml/InstallThemeFromURLDialog.qml
pext/qml/LoadModuleDialog.qml
pext/qml/LoadProfileDialog.qml
pext/qml/LoadThemeDialog.qml
pext/qml/ManageDialog.qml
pext/qml/ManageProfilesDialog.qml
pext/qml/ModuleData.qml
pext/qml/NoModulesInstalledDialog.qml
pext/qml/NoThemesInstalledDialog.qml
pext/qml/OnlyOneProfileDialog.qml
pext/qml/QuestionDialog.qml
pext/qml/RenameProfileDialog.qml
pext/qml/main.qml
pext/qml/repeat_polyfill.js
pext_dev/__main__.py
pext_dev/module/LICENSE
pext_dev/module/__init__.py
pext_dev/theme/LICENSE
pext_dev/theme/theme.conf
Pext-0.35.dist-info/METADATA
Pext-0.35.dist-info/WHEEL
Pext-0.35.dist-info/entry_points.txt
Pext-0.35.dist-info/top_level.txt
Pext-0.35.dist-info/RECORD
