Metadata-Version: 2.1
Name: Pext
Version: 0.35
Summary: Python-based extendable tool
Home-page: https://pext.io/
Author: Sylvia van Os
Author-email: sylvia@hackerchick.me
License: GPLv3+
Keywords: extendable pluggable
Classifier: Development Status :: 4 - Beta
Classifier: Environment :: X11 Applications :: Qt
Classifier: Intended Audience :: Developers
Classifier: Intended Audience :: End Users/Desktop
Classifier: License :: OSI Approved :: GNU General Public License v3 or later (GPLv3+)
Classifier: Operating System :: MacOS
Classifier: Operating System :: POSIX :: Linux
Classifier: Operating System :: Microsoft :: Windows
Classifier: Programming Language :: Python :: 3 :: Only
Classifier: Programming Language :: Python :: 3.5
Classifier: Programming Language :: Python :: 3.6
Classifier: Topic :: Utilities
Requires-Dist: dulwich (==0.20.50)
Requires-Dist: paramiko (==2.12.0)
Requires-Dist: psutil (==5.9.4)
Requires-Dist: pynput (==1.7.6)
Requires-Dist: pyqt5 (==5.15.7)
Requires-Dist: requests (==2.27.1)
Requires-Dist: watchdog (==2.2.0)
Requires-Dist: PyOpenGL (==3.1.6)
